odoo/addons/l10n_it_fiscalcode_crm/README.rst
odoo/addons/l10n_it_fiscalcode_crm/__init__.py
odoo/addons/l10n_it_fiscalcode_crm/__manifest__.py
odoo/addons/l10n_it_fiscalcode_crm/i18n/l10n_it_fiscalcode_crm.pot
odoo/addons/l10n_it_fiscalcode_crm/models/__init__.py
odoo/addons/l10n_it_fiscalcode_crm/models/crm_lead.py
odoo/addons/l10n_it_fiscalcode_crm/readme/CONTRIBUTORS.rst
odoo/addons/l10n_it_fiscalcode_crm/readme/DESCRIPTION.rst
odoo/addons/l10n_it_fiscalcode_crm/static/description/icon.png
odoo/addons/l10n_it_fiscalcode_crm/static/description/index.html
odoo/addons/l10n_it_fiscalcode_crm/tests/__init__.py
odoo/addons/l10n_it_fiscalcode_crm/tests/test_lead.py
odoo/addons/l10n_it_fiscalcode_crm/views/crm_lead.xml
odoo12_addon_l10n_it_fiscalcode_crm-12.0.1.0.2.dist-info/METADATA
odoo12_addon_l10n_it_fiscalcode_crm-12.0.1.0.2.dist-info/WHEEL
odoo12_addon_l10n_it_fiscalcode_crm-12.0.1.0.2.dist-info/top_level.txt
odoo12_addon_l10n_it_fiscalcode_crm-12.0.1.0.2.dist-info/RECORD
